{
  "concept": "harm_principle",
  "domain": "ethics",
  "abstraction_level": 4,
  "corpus": [
    {
      "compression_level": 0,
      "text": "John Stuart Mill's harm principle states that the actions of individuals should only be limited to prevent harm to others. Personal liberty should not be restricted unless one's conduct risks harming another person.",
      "probe_question": "What does the harm principle state?",
      "expected_keywords": ["harm", "others", "liberty", "limit"]
    },
    {
      "compression_level": 1,
      "text": "Actions are restricted only to prevent harm to others.",
      "probe_question": "When can actions be limited under the harm principle?",
      "expected_keywords": ["harm", "others", "restrict"]
    },
    {
      "compression_level": 2,
      "text": "Limit actions to prevent harm.",
      "probe_question": "What is the essence of the harm principle?",
      "expected_keywords": ["limit", "harm"]
    },
    {
      "compression_level": 3,
      "text": "no harm to others",
      "probe_question": "What principle protects others?",
      "expected_keywords": ["harm", "others"]
    },
    {
      "compression_level": 4,
      "text": "prevent harm",
      "probe_question": "Ethics core rule:",
      "expected_keywords": ["harm"]
    }
  ]
}

